{"_ts":[1564665193],"_r":{"breakdown":{"html":{"bytes":[103398],"requests":[66]},"js":{"bytes":[1227293],"requests":[52]},"css":{"bytes":[56899],"requests":[6]},"image":{"bytes":[364045],"requests":[78]},"flash":{"bytes":[0],"requests":[0]},"font":{"bytes":[0],"requests":[0]},"video":{"bytes":[1587848],"requests":[5]},"other":{"bytes":[146977],"requests":[24]}},"date":[1564665193],"domElements":[815],"domInteractive":[2882],"firstPaint":[2932.6699999947],"fullyLoaded":[15587],"id":["190801_CY_07815d219cdfa6944cebef901763dc07"],"loadTime":[4031],"render":[2900],"SpeedIndex":[3278],"TTFB":[454],"videoFrames":[[{"_i":"ms_000000.jpg","_t":0,"_vc":0},{"_i":"ms_002900.jpg","_t":2900,"_vc":84},{"_i":"ms_003000.jpg","_t":3000,"_vc":84},{"_i":"ms_003100.jpg","_t":3100,"_vc":84},{"_i":"ms_003200.jpg","_t":3200,"_vc":84},{"_i":"ms_003300.jpg","_t":3300,"_vc":87},{"_i":"ms_003500.jpg","_t":3500,"_vc":87},{"_i":"ms_003700.jpg","_t":3700,"_vc":88},{"_i":"ms_004000.jpg","_t":4000,"_vc":91},{"_i":"ms_004300.jpg","_t":4300,"_vc":92},{"_i":"ms_004400.jpg","_t":4400,"_vc":92},{"_i":"ms_005800.jpg","_t":5800,"_vc":91},{"_i":"ms_006100.jpg","_t":6100,"_vc":91},{"_i":"ms_006500.jpg","_t":6500,"_vc":92},{"_i":"ms_006700.jpg","_t":6700,"_vc":100}]],"visualComplete":[6700],"lighthouse":[19],"pagespeed":[72]}}